.mailmap
AUTHORS
ChangeLog
MANIFEST.in
README.rst
requirements.txt
setup.py
imks/.gitignore
imks/__init__.py
imks/_version.py
imks/calendars.py
imks/config.py
imks/constants.py
imks/currencies.py
imks/dbpedia.py
imks/doc.py
imks/freebase.py
imks/geolocation.py
imks/imks-old.py
imks/imks.py
imks/imks2.py
imks/imks_ios.py
imks/imks_standalone.py
imks/ipy_dkc.py
imks/jpl.py
imks/lazy.py
imks/magics.py
imks/physics.py
imks/pycalcal.py
imks/shell.py
imks/test_shell.py
imks/test_units.py
imks/transformers.py
imks/units.py
imks/units_fpmath.py
imks/units_math.py
imks/units_mcerp.py
imks/units_mpmath.py
imks/units_numpy.py
imks/units_soerp.py
imks/units_umath.py
imks/uparse.py
imks/wiki.py
imks/wrapper.py
imks/xdict.py
imks.egg-info/PKG-INFO
imks.egg-info/SOURCES.txt
imks.egg-info/dependency_links.txt
imks.egg-info/not-zip-safe
imks.egg-info/pbr.json
imks.egg-info/requires.txt
imks.egg-info/top_level.txt
imks/scripts/Astro.imks
imks/scripts/Startup.imks