Metadata-Version: 1.1
Name: imks
Version: 1.2.6
Summary: An ipython extension to make computations with units
Home-page: https://github.com/astrozot/imks
Author: Marco Lombardi
Author-email: marco.lombardi@gmail.com
License: MIT
Keywords: units physics calculator
Platform: UNKNOWN
Classifier: Development Status :: 3 - Alpha
Classifier: License :: OSI Approved :: MIT License
Classifier: Programming Language :: Python
Classifier: Programming Language :: Python :: 2.7
Classifier: Programming Language :: Python :: 3.5
Classifier: Programming Language :: Python :: 3.6
Classifier: Framework :: IPython
Classifier: Topic :: Scientific/Engineering :: Physics
